tkvariable.py
tkvariable-0.1.0.dist-info/LICENSE
tkvariable-0.1.0.dist-info/METADATA
tkvariable-0.1.0.dist-info/WHEEL
tkvariable-0.1.0.dist-info/top_level.txt
tkvariable-0.1.0.dist-info/RECORD
