Metadata-Version: 2.1
Name: tkvariable
Version: 0.1.0
Summary: Efficient Tkinter variable management with dynamic creation and tracing.
Home-page: https://github.com/code-with-emkay/tkvariable
Author: Emkay
Author-email: mkay.py@gmail.com
Classifier: Programming Language :: Python :: 3
Classifier: License :: OSI Approved :: MIT License
Classifier: Operating System :: OS Independent
Requires-Python: >=3.6
License-File: LICENSE
